sentry_opensearch_nodestore/__init__.py
sentry_opensearch_nodestore/backend.py
sentry_opensearch_nodestore-1.2.0.dist-info/LICENSE
sentry_opensearch_nodestore-1.2.0.dist-info/METADATA
sentry_opensearch_nodestore-1.2.0.dist-info/WHEEL
sentry_opensearch_nodestore-1.2.0.dist-info/RECORD
