Metadata-Version: 2.3
Name: sentry-opensearch-nodestore
Version: 1.2.0
Summary: An Sentry NodeStorage backend for OpenSearch
License: MIT
Keywords: sentry,opensearch,nodestore
Author: airdry
Requires-Python: >=3.8,<4.0
Classifier: License :: OSI Approved :: MIT License
Classifier: Programming Language :: Python :: 3
Classifier: Programming Language :: Python :: 3.8
Classifier: Programming Language :: Python :: 3.9
Classifier: Programming Language :: Python :: 3.10
Classifier: Programming Language :: Python :: 3.11
Classifier: Programming Language :: Python :: 3.12
Classifier: Programming Language :: Python :: 3.13
Requires-Dist: opensearch-py (>=3.0.0,<4.0.0)
Project-URL: Repository, https://github.com/airdry/sentry-opensearch-nodestore
